README.txt
bootstrap.py
buildout.cfg
setup.py
docs/HISTORY.txt
src/munin/__init__.py
src/munin.async.egg-info/PKG-INFO
src/munin.async.egg-info/SOURCES.txt
src/munin.async.egg-info/dependency_links.txt
src/munin.async.egg-info/entry_points.txt
src/munin.async.egg-info/namespace_packages.txt
src/munin.async.egg-info/not-zip-safe
src/munin.async.egg-info/requires.txt
src/munin.async.egg-info/top_level.txt
src/munin/async/__init__.py
src/munin/async/browser.py
src/munin/async/configure.zcml
src/munin/async/plugins.py