Metadata-Version: 1.0
Name: munin.async
Version: 0.4
Summary: Munin plugins for zc.async.
Home-page: http://plone.org/products/munin.async
Author: Jarn AS
Author-email: info@jarn.com
License: GPL
Keywords: plone zope munin monitoring zc.async
Platform: Any
Classifier: Development Status :: 3 - Alpha
Classifier: Programming Language :: Python
Classifier: Framework :: Plone
Classifier: Framework :: ZODB
Classifier: Framework :: Zope2
Classifier: Intended Audience :: Developers
Classifier: Intended Audience :: System Administrators
Classifier: License :: OSI Approved :: GNU General Public License (GPL)
Classifier: Programming Language :: Python
Classifier: Topic :: System :: Networking :: Monitoring
Classifier: Topic :: Software Development :: Libraries :: Python Modules
